[
  {
    "id": "9154af54-4572-4ec9-801d-db6fd1d6b339",
    "imported_at": "2026-06-29T16:17:10.681Z",
    "category": "library",
    "file_name": "personal_library.json",
    "relative_path": "personal_library.json",
    "archive_path": "C:\\Users\\liamb\\AppData\\Roaming\\tiktok-intelligence-hub\\chromium-cache\\tiktok-intelligence-hub\\hub-data\\archive\\library\\2026-06-29T16-17-10-679Z_personal_library.json",
    "import_type": "personal_library",
    "record_count": 0,
    "fingerprint": "3118819:1782749406721.8293"
  },
  {
    "id": "63c05c85-9201-4945-a82d-13f727a18831",
    "imported_at": "2026-06-29T15:42:37.725Z",
    "category": "library",
    "file_name": "personal_library.json",
    "relative_path": "personal_library.json",
    "archive_path": "C:\\Users\\liamb\\AppData\\Roaming\\tiktok-intelligence-hub\\chromium-cache\\tiktok-intelligence-hub\\hub-data\\archive\\library\\2026-06-29T15-42-37-724Z_personal_library.json",
    "import_type": "personal_library",
    "record_count": 0,
    "fingerprint": "1147824:1782747509449.9023"
  },
  {
    "id": "277d4b12-1107-4eb6-a7f8-f79dfad61e65",
    "imported_at": "2026-06-29T15:42:37.714Z",
    "category": "library",
    "file_name": "personal_library-2.json",
    "relative_path": "library/personal_library-2.json",
    "archive_path": "C:\\Users\\liamb\\AppData\\Roaming\\tiktok-intelligence-hub\\chromium-cache\\tiktok-intelligence-hub\\hub-data\\archive\\library\\2026-06-29T15-42-37-712Z_personal_library-2.json",
    "import_type": "library",
    "record_count": 1,
    "fingerprint": "201660:1782747509202.417"
  },
  {
    "id": "dcf72ee6-7602-4a0b-b4ae-d9c1213edff1",
    "imported_at": "2026-06-29T15:38:43.208Z",
    "category": "library",
    "file_name": "personal_library-2.json",
    "relative_path": "library/personal_library-2.json",
    "archive_path": "C:\\Users\\liamb\\AppData\\Roaming\\tiktok-intelligence-hub\\chromium-cache\\tiktok-intelligence-hub\\hub-data\\archive\\library\\2026-06-29T15-38-43-207Z_personal_library-2.json",
    "import_type": "library",
    "record_count": 1,
    "fingerprint": "201660:1782747509202.417"
  },
  {
    "id": "ee28eecd-1f4a-4b6a-85f5-afd3b07d7bdb",
    "imported_at": "2026-06-27T14:12:23.793Z",
    "category": "sales",
    "file_name": "Creator Product List - 20260627140929.xlsx",
    "relative_path": "sales-data/Creator Product List - 20260627140929.xlsx",
    "archive_path": "C:\\Users\\liamb\\AppData\\Roaming\\tiktok-intelligence-hub\\chromium-cache\\tiktok-intelligence-hub\\hub-data\\archive\\sales-data\\2026-06-27T14-12-23-792Z_Creator Product List - 20260627140929.xlsx",
    "import_type": "product_sales",
    "record_count": 39,
    "fingerprint": "33018:1782569372988.0068"
  },
  {
    "id": "d9987863-3caf-451b-9f56-a46c97b0ede5",
    "imported_at": "2026-06-27T14:09:52.807Z",
    "category": "sales",
    "file_name": "Creator Product List - 20260627140929.xlsx",
    "relative_path": "sales-data/Creator Product List - 20260627140929.xlsx",
    "archive_path": "C:\\Users\\liamb\\AppData\\Roaming\\tiktok-intelligence-hub\\chromium-cache\\tiktok-intelligence-hub\\hub-data\\archive\\sales-data\\2026-06-27T14-09-52-805Z_Creator Product List - 20260627140929.xlsx",
    "import_type": "product_sales",
    "record_count": 39,
    "fingerprint": "33018:1782569372988.0068"
  },
  {
    "id": "6aeec23a-4153-4ecd-9cda-362ce8189cc8",
    "imported_at": "2026-06-18T11:31:32.164Z",
    "category": "studio",
    "file_name": "my_studio_data.json",
    "relative_path": "studio/my_studio_data.json",
    "archive_path": "C:\\Users\\liamb\\AppData\\Roaming\\tiktok-intelligence-hub\\chromium-cache\\tiktok-intelligence-hub\\hub-data\\archive\\studio\\2026-06-18T11-31-32-163Z_my_studio_data.json",
    "import_type": "studio",
    "record_count": 1,
    "fingerprint": "2490:1781542423073.2998"
  },
  {
    "id": "1694d8d0-1d8b-49ed-b343-f52dcddaee9d",
    "imported_at": "2026-06-18T11:31:32.162Z",
    "category": "sales",
    "file_name": "Creator Product List - 20260615040049.xlsx",
    "relative_path": "sales-data/Creator Product List - 20260615040049.xlsx",
    "archive_path": "C:\\Users\\liamb\\AppData\\Roaming\\tiktok-intelligence-hub\\chromium-cache\\tiktok-intelligence-hub\\hub-data\\archive\\sales-data\\2026-06-18T11-31-32-162Z_Creator Product List - 20260615040049.xlsx",
    "import_type": "product_sales",
    "record_count": 90,
    "fingerprint": "60085:1781542423073.2998"
  },
  {
    "id": "56e289eb-918a-4dd0-a97a-b3e74844d85d",
    "imported_at": "2026-06-18T11:31:32.145Z",
    "category": "sales",
    "file_name": "Creator Product List - 20260614232031.xlsx",
    "relative_path": "sales-data/Creator Product List - 20260614232031.xlsx",
    "archive_path": "C:\\Users\\liamb\\AppData\\Roaming\\tiktok-intelligence-hub\\chromium-cache\\tiktok-intelligence-hub\\hub-data\\archive\\sales-data\\2026-06-18T11-31-32-144Z_Creator Product List - 20260614232031.xlsx",
    "import_type": "product_sales",
    "record_count": 90,
    "fingerprint": "59503:1781542423072.296"
  },
  {
    "id": "8b515e54-eb6c-44f9-86af-a658dd5c9679",
    "imported_at": "2026-06-18T11:31:32.124Z",
    "category": "library",
    "file_name": "personal_library.json",
    "relative_path": "personal_library.json",
    "archive_path": "C:\\Users\\liamb\\AppData\\Roaming\\tiktok-intelligence-hub\\chromium-cache\\tiktok-intelligence-hub\\hub-data\\archive\\library\\2026-06-18T11-31-32-124Z_personal_library.json",
    "import_type": "personal_library",
    "record_count": 0,
    "fingerprint": "945779:1781627155423.4167"
  },
  {
    "id": "f457ab42-5670-4813-a478-9c1177674461",
    "imported_at": "2026-06-18T11:31:32.115Z",
    "category": "memory",
    "file_name": "positive_memory.json",
    "relative_path": "memory/positive_memory.json",
    "archive_path": "C:\\Users\\liamb\\AppData\\Roaming\\tiktok-intelligence-hub\\chromium-cache\\tiktok-intelligence-hub\\hub-data\\archive\\memory\\2026-06-18T11-31-32-115Z_positive_memory.json",
    "import_type": "positive_memory",
    "record_count": 1,
    "fingerprint": "933:1781627155419.4187"
  },
  {
    "id": "0baceecf-23e6-4c90-b880-567bfcbe961c",
    "imported_at": "2026-06-18T11:31:32.114Z",
    "category": "library",
    "file_name": "personal_library.json",
    "relative_path": "library/personal_library.json",
    "archive_path": "C:\\Users\\liamb\\AppData\\Roaming\\tiktok-intelligence-hub\\chromium-cache\\tiktok-intelligence-hub\\hub-data\\archive\\library\\2026-06-18T11-31-32-113Z_personal_library.json",
    "import_type": "personal_library",
    "record_count": 1,
    "fingerprint": "387952:1781627155419.4187"
  },
  {
    "id": "27b081b6-feaa-4382-8095-47dba103a2c1",
    "imported_at": "2026-06-18T11:31:32.095Z",
    "category": "library",
    "file_name": "personal_library-1.json",
    "relative_path": "library/personal_library-1.json",
    "archive_path": "C:\\Users\\liamb\\AppData\\Roaming\\tiktok-intelligence-hub\\chromium-cache\\tiktok-intelligence-hub\\hub-data\\archive\\library\\2026-06-18T11-31-32-094Z_personal_library-1.json",
    "import_type": "library",
    "record_count": 6,
    "fingerprint": "1333728:1781627155417.3953"
  },
  {
    "id": "722654e6-7f6e-4a4c-9f70-ee1f99000dd0",
    "imported_at": "2026-06-18T11:31:31.727Z",
    "category": "library",
    "file_name": "library.json",
    "relative_path": "library/library.json",
    "archive_path": "C:\\Users\\liamb\\AppData\\Roaming\\tiktok-intelligence-hub\\chromium-cache\\tiktok-intelligence-hub\\hub-data\\archive\\library\\2026-06-18T11-31-31-726Z_library.json",
    "import_type": "library",
    "record_count": 26,
    "fingerprint": "4962384:1781542423071.297"
  },
  {
    "id": "a02a0e91-51bd-4596-8522-a870ca40782d",
    "imported_at": "2026-06-18T11:31:31.351Z",
    "category": "library",
    "file_name": "library-4.json",
    "relative_path": "library/library-4.json",
    "archive_path": "C:\\Users\\liamb\\AppData\\Roaming\\tiktok-intelligence-hub\\chromium-cache\\tiktok-intelligence-hub\\hub-data\\archive\\library\\2026-06-18T11-31-31-351Z_library-4.json",
    "import_type": "library",
    "record_count": 2,
    "fingerprint": "375673:1781668576418.995"
  },
  {
    "id": "7f8e2c39-715c-4bc4-84f0-bf9fa5434b80",
    "imported_at": "2026-06-18T11:31:30.972Z",
    "category": "library",
    "file_name": "library-3.json",
    "relative_path": "library/library-3.json",
    "archive_path": "C:\\Users\\liamb\\AppData\\Roaming\\tiktok-intelligence-hub\\chromium-cache\\tiktok-intelligence-hub\\hub-data\\archive\\library\\2026-06-18T11-31-30-971Z_library-3.json",
    "import_type": "library",
    "record_count": 3,
    "fingerprint": "660309:1781627155412.3528"
  },
  {
    "id": "d5d9575f-95c9-4c17-9cec-ad3b941cc40f",
    "imported_at": "2026-06-18T11:31:30.632Z",
    "category": "library",
    "file_name": "library-2.json",
    "relative_path": "library/library-2.json",
    "archive_path": "C:\\Users\\liamb\\AppData\\Roaming\\tiktok-intelligence-hub\\chromium-cache\\tiktok-intelligence-hub\\hub-data\\archive\\library\\2026-06-18T11-31-30-631Z_library-2.json",
    "import_type": "library",
    "record_count": 32,
    "fingerprint": "3058214:1781627560742.2795"
  },
  {
    "id": "fb6c1716-7830-4ce1-9711-e0af67f79a7f",
    "imported_at": "2026-06-18T11:31:30.284Z",
    "category": "library",
    "file_name": "library-1.json",
    "relative_path": "library/library-1.json",
    "archive_path": "C:\\Users\\liamb\\AppData\\Roaming\\tiktok-intelligence-hub\\chromium-cache\\tiktok-intelligence-hub\\hub-data\\archive\\library\\2026-06-18T11-31-30-283Z_library-1.json",
    "import_type": "library",
    "record_count": 27,
    "fingerprint": "5189325:1781542423053.4707"
  },
  {
    "id": "f8883340-8d20-4261-ba7c-40ffcfa49f61",
    "imported_at": "2026-06-18T11:31:29.932Z",
    "category": "memory",
    "file_name": "positive_memory (3).json",
    "relative_path": "inbox/positive_memory (3).json",
    "archive_path": "C:\\Users\\liamb\\AppData\\Roaming\\tiktok-intelligence-hub\\chromium-cache\\tiktok-intelligence-hub\\hub-data\\archive\\memory\\2026-06-18T11-31-29-932Z_positive_memory (3).json",
    "import_type": "positive_memory",
    "record_count": 4,
    "fingerprint": "3539:1781627155408.3518"
  },
  {
    "id": "252ff649-b131-4a77-b323-09717051f06f",
    "imported_at": "2026-06-18T11:31:29.930Z",
    "category": "sales",
    "file_name": "Creator Product List - 20260614232031.xlsx",
    "relative_path": "Creator Product List - 20260614232031.xlsx",
    "archive_path": "C:\\Users\\liamb\\AppData\\Roaming\\tiktok-intelligence-hub\\chromium-cache\\tiktok-intelligence-hub\\hub-data\\archive\\sales-data\\2026-06-18T11-31-29-930Z_Creator Product List - 20260614232031.xlsx",
    "import_type": "product_sales",
    "record_count": 90,
    "fingerprint": "59503:1781627155277.8684"
  },
  {
    "id": "dcdfa2fb-3427-4ef6-9028-18f3304a38c6",
    "imported_at": "2026-06-18T11:31:29.895Z",
    "category": "compass",
    "file_name": "my_compass_data.json",
    "relative_path": "compass/my_compass_data.json",
    "archive_path": "C:\\Users\\liamb\\AppData\\Roaming\\tiktok-intelligence-hub\\chromium-cache\\tiktok-intelligence-hub\\hub-data\\archive\\compass\\2026-06-18T11-31-29-895Z_my_compass_data.json",
    "import_type": "compass",
    "record_count": 1,
    "fingerprint": "3099:1781542423035.4534"
  },
  {
    "id": "76e955c6-4864-4d06-9677-0346f1eaaeec",
    "imported_at": "2026-06-17T11:00:30.049Z",
    "category": "library",
    "file_name": "library-4.json",
    "relative_path": "library/library-4.json",
    "archive_path": "C:\\Users\\liamb\\AppData\\Roaming\\tiktok-intelligence-hub\\chromium-cache\\tiktok-intelligence-hub\\hub-data\\archive\\library\\2026-06-17T11-00-30-047Z_library-4.json",
    "import_type": "library",
    "record_count": 2,
    "fingerprint": "375673:1781668576418.995"
  },
  {
    "id": "fc8a3337-0239-4072-bc58-98441a2ba86a",
    "imported_at": "2026-06-17T10:56:52.747Z",
    "category": "library",
    "file_name": "library-4.json",
    "relative_path": "library/library-4.json",
    "archive_path": "C:\\Users\\liamb\\AppData\\Roaming\\tiktok-intelligence-hub\\chromium-cache\\tiktok-intelligence-hub\\hub-data\\archive\\library\\2026-06-17T10-56-52-746Z_library-4.json",
    "import_type": "library",
    "record_count": 2,
    "fingerprint": "375673:1781668576418.995"
  },
  {
    "id": "dc426ce2-d537-464d-b797-ef64fe7f7041",
    "imported_at": "2026-06-15T20:49:49.412Z",
    "category": "library",
    "file_name": "personal_library-1.json",
    "relative_path": "library/personal_library-1.json",
    "archive_path": "C:\\Users\\liamb\\AppData\\Roaming\\tiktok-intelligence-hub\\hub-data\\archive\\library\\2026-06-15T20-49-49-407Z_personal_library-1.json",
    "import_type": "library",
    "record_count": 6,
    "fingerprint": "1331190:1781556130576.502"
  },
  {
    "id": "881d6045-11cb-46fe-8924-c4c82c6bce31",
    "imported_at": "2026-06-15T20:49:47.460Z",
    "category": "library",
    "file_name": "library-3.json",
    "relative_path": "library/library-3.json",
    "archive_path": "C:\\Users\\liamb\\AppData\\Roaming\\tiktok-intelligence-hub\\hub-data\\archive\\library\\2026-06-15T20-49-47-458Z_library-3.json",
    "import_type": "library",
    "record_count": 3,
    "fingerprint": "659139:1781556136816.5034"
  },
  {
    "id": "01154a9a-b398-40cd-a802-f28a75ccfe8b",
    "imported_at": "2026-06-15T20:49:46.554Z",
    "category": "memory",
    "file_name": "positive_memory (3).json",
    "relative_path": "inbox/positive_memory (3).json",
    "archive_path": "C:\\Users\\liamb\\AppData\\Roaming\\tiktok-intelligence-hub\\hub-data\\archive\\memory\\2026-06-15T20-49-46-552Z_positive_memory (3).json",
    "import_type": "positive_memory",
    "record_count": 4,
    "fingerprint": "3454:1781556128405.9663"
  },
  {
    "id": "3f242d2c-bf78-4c1d-a74b-875a7fb93290",
    "imported_at": "2026-06-15T20:49:44.483Z",
    "category": "library",
    "file_name": "library-3.json",
    "relative_path": "library/library-3.json",
    "archive_path": "C:\\Users\\liamb\\AppData\\Roaming\\tiktok-intelligence-hub\\hub-data\\archive\\library\\2026-06-15T20-49-44-481Z_library-3.json",
    "import_type": "library",
    "record_count": 3,
    "fingerprint": "659139:1781556136816.5034"
  },
  {
    "id": "807dd16a-a111-4b24-89e8-6b7af4448b3d",
    "imported_at": "2026-06-15T20:49:43.525Z",
    "category": "memory",
    "file_name": "positive_memory (3).json",
    "relative_path": "inbox/positive_memory (3).json",
    "archive_path": "C:\\Users\\liamb\\AppData\\Roaming\\tiktok-intelligence-hub\\hub-data\\archive\\memory\\2026-06-15T20-49-43-523Z_positive_memory (3).json",
    "import_type": "positive_memory",
    "record_count": 4,
    "fingerprint": "3454:1781556128405.9663"
  },
  {
    "id": "05bdb309-0374-4222-a1a5-5bddc359842f",
    "imported_at": "2026-06-15T20:49:41.799Z",
    "category": "library",
    "file_name": "library-3.json",
    "relative_path": "library/library-3.json",
    "archive_path": "C:\\Users\\liamb\\AppData\\Roaming\\tiktok-intelligence-hub\\hub-data\\archive\\library\\2026-06-15T20-49-41-797Z_library-3.json",
    "import_type": "library",
    "record_count": 3,
    "fingerprint": "659139:1781556136816.5034"
  },
  {
    "id": "b1e899ae-ae2b-45c8-8d31-3d6af8295d4a",
    "imported_at": "2026-06-15T20:49:40.776Z",
    "category": "memory",
    "file_name": "positive_memory (3).json",
    "relative_path": "inbox/positive_memory (3).json",
    "archive_path": "C:\\Users\\liamb\\AppData\\Roaming\\tiktok-intelligence-hub\\hub-data\\archive\\memory\\2026-06-15T20-49-40-773Z_positive_memory (3).json",
    "import_type": "positive_memory",
    "record_count": 4,
    "fingerprint": "3454:1781556128405.9663"
  },
  {
    "id": "b093c9c4-7ccc-4893-bf91-e9ae7f5346c4",
    "imported_at": "2026-06-15T20:49:39.072Z",
    "category": "library",
    "file_name": "library-3.json",
    "relative_path": "library/library-3.json",
    "archive_path": "C:\\Users\\liamb\\AppData\\Roaming\\tiktok-intelligence-hub\\hub-data\\archive\\library\\2026-06-15T20-49-39-069Z_library-3.json",
    "import_type": "library",
    "record_count": 3,
    "fingerprint": "659139:1781556136816.5034"
  },
  {
    "id": "c8eaf9eb-9cd5-4481-b852-b04207c71600",
    "imported_at": "2026-06-15T20:49:38.007Z",
    "category": "memory",
    "file_name": "positive_memory (3).json",
    "relative_path": "inbox/positive_memory (3).json",
    "archive_path": "C:\\Users\\liamb\\AppData\\Roaming\\tiktok-intelligence-hub\\hub-data\\archive\\memory\\2026-06-15T20-49-38-004Z_positive_memory (3).json",
    "import_type": "positive_memory",
    "record_count": 4,
    "fingerprint": "3454:1781556128405.9663"
  },
  {
    "id": "6e26eef1-c4e0-471b-af34-5380ffbe4405",
    "imported_at": "2026-06-15T20:42:46.921Z",
    "category": "memory",
    "file_name": "positive_memory (3).json",
    "relative_path": "inbox/positive_memory (3).json",
    "archive_path": "C:\\Users\\liamb\\AppData\\Roaming\\tiktok-intelligence-hub\\hub-data\\archive\\memory\\2026-06-15T20-42-46-919Z_positive_memory (3).json",
    "import_type": "positive_memory",
    "record_count": 4,
    "fingerprint": "3454:1781556128405.9663"
  },
  {
    "id": "352e5c72-9b6e-4236-956a-6615e97215c6",
    "imported_at": "2026-06-15T20:42:46.906Z",
    "category": "library",
    "file_name": "personal_library-1.json",
    "relative_path": "library/personal_library-1.json",
    "archive_path": "C:\\Users\\liamb\\AppData\\Roaming\\tiktok-intelligence-hub\\hub-data\\archive\\library\\2026-06-15T20-42-46-903Z_personal_library-1.json",
    "import_type": "library",
    "record_count": 6,
    "fingerprint": "1331190:1781556130576.502"
  },
  {
    "id": "af1df203-6874-4792-b6bd-ab3409d0ca93",
    "imported_at": "2026-06-15T20:42:45.993Z",
    "category": "library",
    "file_name": "library-3.json",
    "relative_path": "library/library-3.json",
    "archive_path": "C:\\Users\\liamb\\AppData\\Roaming\\tiktok-intelligence-hub\\hub-data\\archive\\library\\2026-06-15T20-42-45-990Z_library-3.json",
    "import_type": "library",
    "record_count": 3,
    "fingerprint": "659139:1781556136816.5034"
  },
  {
    "id": "66695272-61e4-4e80-8e33-de6727874b0b",
    "imported_at": "2026-06-15T20:42:36.184Z",
    "category": "library",
    "file_name": "personal_library.json",
    "relative_path": "personal_library.json",
    "archive_path": "C:\\Users\\liamb\\AppData\\Roaming\\tiktok-intelligence-hub\\hub-data\\archive\\library\\2026-06-15T20-42-36-182Z_personal_library.json",
    "import_type": "personal_library",
    "record_count": 4,
    "fingerprint": "945779:1781556130837.7886"
  },
  {
    "id": "b31913b6-6f6a-4bf0-8bd6-96c81c69c6c4",
    "imported_at": "2026-06-15T20:21:15.391Z",
    "category": "studio",
    "file_name": "my_studio_data.json",
    "relative_path": "studio/my_studio_data.json",
    "archive_path": "C:\\Users\\liamb\\AppData\\Roaming\\tiktok-intelligence-hub\\hub-data\\archive\\studio\\2026-06-15T20-21-15-389Z_my_studio_data.json",
    "import_type": "studio",
    "record_count": 1,
    "fingerprint": "2380:1781479553499.301"
  },
  {
    "id": "0262973f-fce5-4d01-aea6-9dbecae6d4b7",
    "imported_at": "2026-06-15T20:21:15.386Z",
    "category": "sales",
    "file_name": "Creator Product List - 20260615040049.xlsx",
    "relative_path": "sales-data/Creator Product List - 20260615040049.xlsx",
    "archive_path": "C:\\Users\\liamb\\AppData\\Roaming\\tiktok-intelligence-hub\\hub-data\\archive\\sales-data\\2026-06-15T20-21-15-384Z_Creator Product List - 20260615040049.xlsx",
    "import_type": "product_sales",
    "record_count": 90,
    "fingerprint": "60085:1781496054706.812"
  },
  {
    "id": "2c5cfc0c-8357-458e-bc11-75ee827227a4",
    "imported_at": "2026-06-15T20:21:15.344Z",
    "category": "sales",
    "file_name": "Creator Product List - 20260614232031.xlsx",
    "relative_path": "sales-data/Creator Product List - 20260614232031.xlsx",
    "archive_path": "C:\\Users\\liamb\\AppData\\Roaming\\tiktok-intelligence-hub\\hub-data\\archive\\sales-data\\2026-06-15T20-21-15-342Z_Creator Product List - 20260614232031.xlsx",
    "import_type": "product_sales",
    "record_count": 90,
    "fingerprint": "59503:1781479234400.721"
  },
  {
    "id": "fa122b46-21d6-4528-9a97-d3f9303a96d9",
    "imported_at": "2026-06-15T20:21:15.276Z",
    "category": "memory",
    "file_name": "positive_memory.json",
    "relative_path": "memory/positive_memory.json",
    "archive_path": "C:\\Users\\liamb\\AppData\\Roaming\\tiktok-intelligence-hub\\hub-data\\archive\\memory\\2026-06-15T20-21-15-273Z_positive_memory.json",
    "import_type": "positive_memory",
    "record_count": 1,
    "fingerprint": "911:1781554573671.5356"
  },
  {
    "id": "9620338c-ba9b-485c-8b6a-174bcceff8ae",
    "imported_at": "2026-06-15T20:21:15.271Z",
    "category": "library",
    "file_name": "personal_library.json",
    "relative_path": "library/personal_library.json",
    "archive_path": "C:\\Users\\liamb\\AppData\\Roaming\\tiktok-intelligence-hub\\hub-data\\archive\\library\\2026-06-15T20-21-15-268Z_personal_library.json",
    "import_type": "personal_library",
    "record_count": 0,
    "fingerprint": "386968:1781554810841.6956"
  },
  {
    "id": "e3908b42-c14d-4bf3-bb5f-566d6700e966",
    "imported_at": "2026-06-15T20:21:15.264Z",
    "category": "library",
    "file_name": "library.json",
    "relative_path": "library/library.json",
    "archive_path": "C:\\Users\\liamb\\AppData\\Roaming\\tiktok-intelligence-hub\\hub-data\\archive\\library\\2026-06-15T20-21-15-259Z_library.json",
    "import_type": "library",
    "record_count": 26,
    "fingerprint": "4956382:1781478607505.1772"
  },
  {
    "id": "fdd3e60a-affc-4992-8d27-24fd06610e2f",
    "imported_at": "2026-06-15T20:21:14.287Z",
    "category": "library",
    "file_name": "library-2.json",
    "relative_path": "library/library-2.json",
    "archive_path": "C:\\Users\\liamb\\AppData\\Roaming\\tiktok-intelligence-hub\\hub-data\\archive\\library\\2026-06-15T20-21-14-284Z_library-2.json",
    "import_type": "library",
    "record_count": 1,
    "fingerprint": "192793:1781554250822.9248"
  },
  {
    "id": "b3773646-4996-4726-8cac-bc723d260297",
    "imported_at": "2026-06-15T20:21:13.298Z",
    "category": "library",
    "file_name": "library-1.json",
    "relative_path": "library/library-1.json",
    "archive_path": "C:\\Users\\liamb\\AppData\\Roaming\\tiktok-intelligence-hub\\hub-data\\archive\\library\\2026-06-15T20-21-13-291Z_library-1.json",
    "import_type": "library",
    "record_count": 27,
    "fingerprint": "5182934:1781526623819.8765"
  },
  {
    "id": "6160236d-47d7-4935-b139-87dc2265bf47",
    "imported_at": "2026-06-15T20:21:12.291Z",
    "category": "compass",
    "file_name": "my_compass_data.json",
    "relative_path": "compass/my_compass_data.json",
    "archive_path": "C:\\Users\\liamb\\AppData\\Roaming\\tiktok-intelligence-hub\\hub-data\\archive\\compass\\2026-06-15T20-21-12-288Z_my_compass_data.json",
    "import_type": "compass",
    "record_count": 1,
    "fingerprint": "2970:1781479575574.1604"
  },
  {
    "id": "9c48fa63-7b02-4ff5-85f5-beb69f10315a",
    "imported_at": "2026-06-15T20:21:05.771Z",
    "category": "library",
    "file_name": "library-2.json",
    "relative_path": "library/library-2.json",
    "archive_path": "C:\\Users\\liamb\\AppData\\Roaming\\tiktok-intelligence-hub\\hub-data\\archive\\library\\2026-06-15T20-21-05-768Z_library-2.json",
    "import_type": "library",
    "record_count": 1,
    "fingerprint": "192793:1781554250822.9248"
  },
  {
    "id": "5cd12e22-4b77-4703-8f2a-9c0d28ab4154",
    "imported_at": "2026-06-15T20:21:02.859Z",
    "category": "memory",
    "file_name": "positive_memory.json",
    "relative_path": "memory/positive_memory.json",
    "archive_path": "C:\\Users\\liamb\\AppData\\Roaming\\tiktok-intelligence-hub\\hub-data\\archive\\memory\\2026-06-15T20-21-02-857Z_positive_memory.json",
    "import_type": "positive_memory",
    "record_count": 1,
    "fingerprint": "911:1781554573671.5356"
  },
  {
    "id": "da160d33-d554-4607-85e5-753170d09c60",
    "imported_at": "2026-06-15T20:21:02.843Z",
    "category": "library",
    "file_name": "personal_library.json",
    "relative_path": "library/personal_library.json",
    "archive_path": "C:\\Users\\liamb\\AppData\\Roaming\\tiktok-intelligence-hub\\hub-data\\archive\\library\\2026-06-15T20-21-02-840Z_personal_library.json",
    "import_type": "personal_library",
    "record_count": 2,
    "fingerprint": "386968:1781554810841.6956"
  },
  {
    "id": "c30778fd-3683-4b5e-b017-908246879f26",
    "imported_at": "2026-06-15T20:06:40.234Z",
    "category": "studio",
    "file_name": "my_studio_data.json",
    "relative_path": "studio/my_studio_data.json",
    "archive_path": "C:\\Users\\liamb\\AppData\\Roaming\\tiktok-intelligence-hub\\hub-data\\archive\\studio\\2026-06-15T20-06-40-231Z_my_studio_data.json",
    "import_type": "studio",
    "record_count": 1,
    "fingerprint": "2380:1781479553499.301"
  },
  {
    "id": "171ce616-e8aa-44f6-b40e-212cafcfee7b",
    "imported_at": "2026-06-15T20:06:40.228Z",
    "category": "sales",
    "file_name": "Creator Product List - 20260615040049.xlsx",
    "relative_path": "sales-data/Creator Product List - 20260615040049.xlsx",
    "archive_path": "C:\\Users\\liamb\\AppData\\Roaming\\tiktok-intelligence-hub\\hub-data\\archive\\sales-data\\2026-06-15T20-06-40-226Z_Creator Product List - 20260615040049.xlsx",
    "import_type": "product_sales",
    "record_count": 90,
    "fingerprint": "60085:1781496054706.812"
  },
  {
    "id": "372fe39a-7e11-423b-a065-23894ecc2200",
    "imported_at": "2026-06-15T20:06:40.173Z",
    "category": "sales",
    "file_name": "Creator Product List - 20260614232031.xlsx",
    "relative_path": "sales-data/Creator Product List - 20260614232031.xlsx",
    "archive_path": "C:\\Users\\liamb\\AppData\\Roaming\\tiktok-intelligence-hub\\hub-data\\archive\\sales-data\\2026-06-15T20-06-40-170Z_Creator Product List - 20260614232031.xlsx",
    "import_type": "product_sales",
    "record_count": 90,
    "fingerprint": "59503:1781479234400.721"
  },
  {
    "id": "7c84d61f-71b3-483a-a662-00ecba3b2000",
    "imported_at": "2026-06-15T20:06:40.095Z",
    "category": "library",
    "file_name": "library.json",
    "relative_path": "library/library.json",
    "archive_path": "C:\\Users\\liamb\\AppData\\Roaming\\tiktok-intelligence-hub\\hub-data\\archive\\library\\2026-06-15T20-06-40-091Z_library.json",
    "import_type": "library",
    "record_count": 26,
    "fingerprint": "4956382:1781478607505.1772"
  },
  {
    "id": "b8db70d5-727a-42dc-919f-25a8c6190318",
    "imported_at": "2026-06-15T20:06:38.795Z",
    "category": "library",
    "file_name": "library-1.json",
    "relative_path": "library/library-1.json",
    "archive_path": "C:\\Users\\liamb\\AppData\\Roaming\\tiktok-intelligence-hub\\hub-data\\archive\\library\\2026-06-15T20-06-38-789Z_library-1.json",
    "import_type": "library",
    "record_count": 27,
    "fingerprint": "5182934:1781526623819.8765"
  },
  {
    "id": "77929de1-32f6-40ce-814d-579969539aa6",
    "imported_at": "2026-06-15T20:06:37.495Z",
    "category": "compass",
    "file_name": "my_compass_data.json",
    "relative_path": "compass/my_compass_data.json",
    "archive_path": "C:\\Users\\liamb\\AppData\\Roaming\\tiktok-intelligence-hub\\hub-data\\archive\\compass\\2026-06-15T20-06-37-492Z_my_compass_data.json",
    "import_type": "compass",
    "record_count": 1,
    "fingerprint": "2970:1781479575574.1604"
  },
  {
    "id": "62072d88-18b8-4f1b-b1a2-37cf1b740d1d",
    "imported_at": "2026-06-15T20:06:27.110Z",
    "category": "studio",
    "file_name": "my_studio_data.json",
    "relative_path": "studio/my_studio_data.json",
    "archive_path": "C:\\Users\\liamb\\AppData\\Roaming\\tiktok-intelligence-hub\\hub-data\\archive\\studio\\2026-06-15T20-06-27-107Z_my_studio_data.json",
    "import_type": "studio",
    "record_count": 1,
    "fingerprint": "2380:1781479553499.301"
  },
  {
    "id": "62097948-9967-467d-a513-ba1674115ea1",
    "imported_at": "2026-06-15T20:06:27.103Z",
    "category": "sales",
    "file_name": "Creator Product List - 20260615040049.xlsx",
    "relative_path": "sales-data/Creator Product List - 20260615040049.xlsx",
    "archive_path": "C:\\Users\\liamb\\AppData\\Roaming\\tiktok-intelligence-hub\\hub-data\\archive\\sales-data\\2026-06-15T20-06-27-100Z_Creator Product List - 20260615040049.xlsx",
    "import_type": "product_sales",
    "record_count": 90,
    "fingerprint": "60085:1781496054706.812"
  },
  {
    "id": "17ca5d26-9eba-44e3-988f-970f24bc9da7",
    "imported_at": "2026-06-15T20:06:27.045Z",
    "category": "sales",
    "file_name": "Creator Product List - 20260614232031.xlsx",
    "relative_path": "sales-data/Creator Product List - 20260614232031.xlsx",
    "archive_path": "C:\\Users\\liamb\\AppData\\Roaming\\tiktok-intelligence-hub\\hub-data\\archive\\sales-data\\2026-06-15T20-06-27-042Z_Creator Product List - 20260614232031.xlsx",
    "import_type": "product_sales",
    "record_count": 90,
    "fingerprint": "59503:1781479234400.721"
  },
  {
    "id": "9fb1e1e9-ec3e-406e-94ec-73bdf2083aa6",
    "imported_at": "2026-06-15T20:06:26.935Z",
    "category": "library",
    "file_name": "library.json",
    "relative_path": "library/library.json",
    "archive_path": "C:\\Users\\liamb\\AppData\\Roaming\\tiktok-intelligence-hub\\hub-data\\archive\\library\\2026-06-15T20-06-26-929Z_library.json",
    "import_type": "library",
    "record_count": 26,
    "fingerprint": "4956382:1781478607505.1772"
  },
  {
    "id": "d3b9ebb8-d016-4b0e-929e-e0178f1a333e",
    "imported_at": "2026-06-15T20:06:25.530Z",
    "category": "library",
    "file_name": "library-1.json",
    "relative_path": "library/library-1.json",
    "archive_path": "C:\\Users\\liamb\\AppData\\Roaming\\tiktok-intelligence-hub\\hub-data\\archive\\library\\2026-06-15T20-06-25-525Z_library-1.json",
    "import_type": "library",
    "record_count": 27,
    "fingerprint": "5182934:1781526623819.8765"
  },
  {
    "id": "1e78fb35-2762-4d69-894e-a0e4ef399d35",
    "imported_at": "2026-06-15T20:06:24.224Z",
    "category": "compass",
    "file_name": "my_compass_data.json",
    "relative_path": "compass/my_compass_data.json",
    "archive_path": "C:\\Users\\liamb\\AppData\\Roaming\\tiktok-intelligence-hub\\hub-data\\archive\\compass\\2026-06-15T20-06-24-221Z_my_compass_data.json",
    "import_type": "compass",
    "record_count": 1,
    "fingerprint": "2970:1781479575574.1604"
  },
  {
    "id": "bf856875-ce54-46da-ab45-261ee52ee84a",
    "imported_at": "2026-06-15T18:41:38.056Z",
    "category": "library",
    "file_name": "library-2.json",
    "relative_path": "library/library-2.json",
    "archive_path": "C:\\Users\\liamb\\AppData\\Roaming\\tiktok-intelligence-hub\\chromium-cache\\tiktok-intelligence-hub\\hub-data\\archive\\library\\2026-06-15T18-41-38-054Z_library-2.json",
    "import_type": "library",
    "record_count": 32,
    "fingerprint": "3049230:1781548362654.6902"
  },
  {
    "id": "c1502058-2ca9-4f7a-b4f0-3391d12d1375",
    "imported_at": "2026-06-15T18:36:12.277Z",
    "category": "library",
    "file_name": "library-2.json",
    "relative_path": "library/library-2.json",
    "archive_path": "C:\\Users\\liamb\\AppData\\Roaming\\tiktok-intelligence-hub\\chromium-cache\\tiktok-intelligence-hub\\hub-data\\archive\\library\\2026-06-15T18-36-12-275Z_library-2.json",
    "import_type": "library",
    "record_count": 32,
    "fingerprint": "3049230:1781548362654.6902"
  },
  {
    "id": "86f10e34-3f7f-4708-a237-4f1db4c77668",
    "imported_at": "2026-06-15T18:29:58.746Z",
    "category": "studio",
    "file_name": "my_studio_data.json",
    "relative_path": "studio/my_studio_data.json",
    "archive_path": "C:\\Users\\liamb\\AppData\\Roaming\\tiktok-intelligence-hub\\chromium-cache\\tiktok-intelligence-hub\\hub-data\\archive\\studio\\2026-06-15T18-29-58-746Z_my_studio_data.json",
    "import_type": "studio",
    "record_count": 1,
    "fingerprint": "2490:1781542423073.2998"
  },
  {
    "id": "29cc61fb-019f-4413-9568-bb266aa083d6",
    "imported_at": "2026-06-15T18:29:58.744Z",
    "category": "sales",
    "file_name": "Creator Product List - 20260615040049.xlsx",
    "relative_path": "sales-data/Creator Product List - 20260615040049.xlsx",
    "archive_path": "C:\\Users\\liamb\\AppData\\Roaming\\tiktok-intelligence-hub\\chromium-cache\\tiktok-intelligence-hub\\hub-data\\archive\\sales-data\\2026-06-15T18-29-58-744Z_Creator Product List - 20260615040049.xlsx",
    "import_type": "product_sales",
    "record_count": 90,
    "fingerprint": "60085:1781542423073.2998"
  },
  {
    "id": "561d4b7f-39b1-45f9-973e-0b732ebbf32e",
    "imported_at": "2026-06-15T18:29:58.722Z",
    "category": "sales",
    "file_name": "Creator Product List - 20260614232031.xlsx",
    "relative_path": "sales-data/Creator Product List - 20260614232031.xlsx",
    "archive_path": "C:\\Users\\liamb\\AppData\\Roaming\\tiktok-intelligence-hub\\chromium-cache\\tiktok-intelligence-hub\\hub-data\\archive\\sales-data\\2026-06-15T18-29-58-722Z_Creator Product List - 20260614232031.xlsx",
    "import_type": "product_sales",
    "record_count": 90,
    "fingerprint": "59503:1781542423072.296"
  },
  {
    "id": "6293b8c8-bdc0-4a5f-a96d-cdb0dbd5833b",
    "imported_at": "2026-06-15T18:29:58.687Z",
    "category": "library",
    "file_name": "library.json",
    "relative_path": "library/library.json",
    "archive_path": "C:\\Users\\liamb\\AppData\\Roaming\\tiktok-intelligence-hub\\chromium-cache\\tiktok-intelligence-hub\\hub-data\\archive\\library\\2026-06-15T18-29-58-685Z_library.json",
    "import_type": "library",
    "record_count": 26,
    "fingerprint": "4962384:1781542423071.297"
  },
  {
    "id": "a0ec7674-5a43-4904-9557-008de19e6a20",
    "imported_at": "2026-06-15T18:29:58.542Z",
    "category": "library",
    "file_name": "library-1.json",
    "relative_path": "library/library-1.json",
    "archive_path": "C:\\Users\\liamb\\AppData\\Roaming\\tiktok-intelligence-hub\\chromium-cache\\tiktok-intelligence-hub\\hub-data\\archive\\library\\2026-06-15T18-29-58-541Z_library-1.json",
    "import_type": "library",
    "record_count": 27,
    "fingerprint": "5189325:1781542423053.4707"
  },
  {
    "id": "41a68268-558c-4f90-87b1-3f113b36d518",
    "imported_at": "2026-06-15T18:29:58.402Z",
    "category": "compass",
    "file_name": "my_compass_data.json",
    "relative_path": "compass/my_compass_data.json",
    "archive_path": "C:\\Users\\liamb\\AppData\\Roaming\\tiktok-intelligence-hub\\chromium-cache\\tiktok-intelligence-hub\\hub-data\\archive\\compass\\2026-06-15T18-29-58-401Z_my_compass_data.json",
    "import_type": "compass",
    "record_count": 1,
    "fingerprint": "3099:1781542423035.4534"
  },
  {
    "id": "5c022fda-8ed4-49f5-bf93-607b82b03321",
    "imported_at": "2026-06-15T16:57:07.437Z",
    "category": "studio",
    "file_name": "my_studio_data.json",
    "relative_path": "studio/my_studio_data.json",
    "archive_path": "C:\\Users\\liamb\\AppData\\Roaming\\tiktok-intelligence-hub\\chromium-cache\\tiktok-intelligence-hub\\hub-data\\archive\\studio\\2026-06-15T16-57-07-437Z_my_studio_data.json",
    "import_type": "studio",
    "record_count": 1,
    "fingerprint": "2490:1781542423073.2998"
  },
  {
    "id": "fe6a9e89-e90a-42a3-996e-47aeafae17f9",
    "imported_at": "2026-06-15T16:57:07.435Z",
    "category": "sales",
    "file_name": "Creator Product List - 20260615040049.xlsx",
    "relative_path": "sales-data/Creator Product List - 20260615040049.xlsx",
    "archive_path": "C:\\Users\\liamb\\AppData\\Roaming\\tiktok-intelligence-hub\\chromium-cache\\tiktok-intelligence-hub\\hub-data\\archive\\sales-data\\2026-06-15T16-57-07-435Z_Creator Product List - 20260615040049.xlsx",
    "import_type": "product_sales",
    "record_count": 90,
    "fingerprint": "60085:1781542423073.2998"
  },
  {
    "id": "9d3e25f4-1d7b-4fd7-8f00-28cb96e5d525",
    "imported_at": "2026-06-15T16:57:07.414Z",
    "category": "sales",
    "file_name": "Creator Product List - 20260614232031.xlsx",
    "relative_path": "sales-data/Creator Product List - 20260614232031.xlsx",
    "archive_path": "C:\\Users\\liamb\\AppData\\Roaming\\tiktok-intelligence-hub\\chromium-cache\\tiktok-intelligence-hub\\hub-data\\archive\\sales-data\\2026-06-15T16-57-07-414Z_Creator Product List - 20260614232031.xlsx",
    "import_type": "product_sales",
    "record_count": 90,
    "fingerprint": "59503:1781542423072.296"
  },
  {
    "id": "3ceca00b-56bc-4728-a072-e6f205907492",
    "imported_at": "2026-06-15T16:57:07.379Z",
    "category": "library",
    "file_name": "library.json",
    "relative_path": "library/library.json",
    "archive_path": "C:\\Users\\liamb\\AppData\\Roaming\\tiktok-intelligence-hub\\chromium-cache\\tiktok-intelligence-hub\\hub-data\\archive\\library\\2026-06-15T16-57-07-377Z_library.json",
    "import_type": "library",
    "record_count": 26,
    "fingerprint": "4962384:1781542423071.297"
  },
  {
    "id": "b78cc476-7dbb-4419-b89f-32b44efe482e",
    "imported_at": "2026-06-15T16:57:07.238Z",
    "category": "library",
    "file_name": "library-1.json",
    "relative_path": "library/library-1.json",
    "archive_path": "C:\\Users\\liamb\\AppData\\Roaming\\tiktok-intelligence-hub\\chromium-cache\\tiktok-intelligence-hub\\hub-data\\archive\\library\\2026-06-15T16-57-07-236Z_library-1.json",
    "import_type": "library",
    "record_count": 27,
    "fingerprint": "5189325:1781542423053.4707"
  },
  {
    "id": "173cb368-5180-4ad9-b79f-b373e80f31ed",
    "imported_at": "2026-06-15T16:57:07.089Z",
    "category": "compass",
    "file_name": "my_compass_data.json",
    "relative_path": "compass/my_compass_data.json",
    "archive_path": "C:\\Users\\liamb\\AppData\\Roaming\\tiktok-intelligence-hub\\chromium-cache\\tiktok-intelligence-hub\\hub-data\\archive\\compass\\2026-06-15T16-57-07-089Z_my_compass_data.json",
    "import_type": "compass",
    "record_count": 1,
    "fingerprint": "3099:1781542423035.4534"
  }
]